gptchangelog/__init__.py
gptchangelog/__main__.py
gptchangelog/cli.py
gptchangelog/config.py
gptchangelog/enhanced_git_utils.py
gptchangelog/enhanced_openai_utils.py
gptchangelog/git_utils.py
gptchangelog/openai_utils.py
gptchangelog/textual_ui.py
gptchangelog/utils.py
gptchangelog/templates/changelog_prompt.txt
gptchangelog/templates/commits_prompt.txt
gptchangelog/templates/enhanced_changelog_prompt.txt
gptchangelog/templates/enhanced_commits_prompt.txt
gptchangelog/templates/enhanced_version_prompt.txt
gptchangelog/templates/es_changelog_prompt.txt
gptchangelog/templates/fr_changelog_prompt.txt
gptchangelog/templates/version_prompt.txt
gptchangelog-0.10.1.dist-info/licenses/LICENSE
gptchangelog-0.10.1.dist-info/METADATA
gptchangelog-0.10.1.dist-info/WHEEL
gptchangelog-0.10.1.dist-info/entry_points.txt
gptchangelog-0.10.1.dist-info/top_level.txt
gptchangelog-0.10.1.dist-info/RECORD
