Metadata-Version: 2.4
Name: gptchangelog
Version: 0.10.1
Summary: Automatically generate a changelog using AI
Author-email: Xavier Jodoin <python@jodoin.me>
License: MIT
Project-URL: GitHub, https://github.com/xjodoin/gptchangelog
Classifier: Development Status :: 5 - Production/Stable
Classifier: Programming Language :: Python
Classifier: Programming Language :: Python :: 3 :: Only
Classifier: Environment :: Console
Classifier: Intended Audience :: Developers
Classifier: License :: OSI Approved :: MIT License
Classifier: Topic :: Software Development
Classifier: Topic :: Terminals
Classifier: Topic :: Text Processing
Classifier: Topic :: Utilities
Requires-Python: >=3.12
License-File: LICENSE
Requires-Dist: openai>=1.52.0
Requires-Dist: gitpython>=3.1.40
Requires-Dist: configparser>=6.0.0
Requires-Dist: tiktoken>=0.8.0
Requires-Dist: rich>=13.9.0
Requires-Dist: textual>=0.58.0
Requires-Dist: importlib_metadata>=1.0.0; python_version < "3.8"
Provides-Extra: dev
Requires-Dist: pytest; extra == "dev"
Requires-Dist: pytest-cov; extra == "dev"
Requires-Dist: black; extra == "dev"
Requires-Dist: isort; extra == "dev"
Requires-Dist: mypy; extra == "dev"
Provides-Extra: docs
Requires-Dist: mkdocs-material; extra == "docs"
Requires-Dist: mkdocstrings[python]; extra == "docs"
Requires-Dist: mkdocs-git-revision-date-localized-plugin; extra == "docs"
Provides-Extra: release
Requires-Dist: build; extra == "release"
Requires-Dist: twine; extra == "release"
Dynamic: license-file
